Workbook

Sheet Mass Upload Tool
A1: CSR TYPE | B1: For Competitive CSRs: Please fill out Columns A-D | C1: Limit of 100 Parts Per Form | E1: =VLOOKUP('Mass Upload Tool'!D1,'Competitor Options '!$B:$B,1)
E2: =VLOOKUP('Mass Upload Tool'!D2,'Competitor Options '!$B:$B,1)
E3: =VLOOKUP('Mass Upload Tool'!D3,'Competitor Options '!$B:$B,1)
A4: Part Number | B4: Competitor Price | C4: Competitor Part | D4: Competitor Name | E4: Competitor Code
E5: =IF(ISBLANK(D5),"",VLOOKUP(D5,'Competitor Options '!$A:$B,2,FALSE))
E6: =IF(ISBLANK(D6),"",VLOOKUP(D6,'Competitor Options '!$A:$B,2,FALSE))
E7: =IF(ISBLANK(D7),"",VLOOKUP(D7,'Competitor Options '!$A:$B,2,FALSE))
E8: =IF(ISBLANK(D8),"",VLOOKUP(D8,'Competitor Options '!$A:$B,2,FALSE))
E9: =IF(ISBLANK(D9),"",VLOOKUP(D9,'Competitor Options '!$A:$B,2,FALSE))
E10: =IF(ISBLANK(D10),"",VLOOKUP(D10,'Competitor Options '!$A:$B,2,FALSE))
E11: =IF(ISBLANK(D11),"",VLOOKUP(D11,'Competitor Options '!$A:$B,2,FALSE))
E12: =IF(ISBLANK(D12),"",VLOOKUP(D12,'Competitor Options '!$A:$B,2,FALSE))
E13: =IF(ISBLANK(D13),"",VLOOKUP(D13,'Competitor Options '!$A:$B,2,FALSE))
E14: =IF(ISBLANK(D14),"",VLOOKUP(D14,'Competitor Options '!$A:$B,2,FALSE))
E15: =IF(ISBLANK(D15),"",VLOOKUP(D15,'Competitor Options '!$A:$B,2,FALSE))
E16: =IF(ISBLANK(D16),"",VLOOKUP(D16,'Competitor Options '!$A:$B,2,FALSE))
... E105: =IF(ISBLANK(D105),"",VLOOKUP(D105,'Competitor Options '!$A:$B,2,FALSE))

Sheet Information
A1: Hide Information and Competitor Sheets and Protect Workbook | B1: Afterwards Protect Sheet
A2: Wreck
A3: Blind
A4: Competitive
A6: For Column A formatting | B6: "=NOT( OR( NOT($A$2="Competitive"), AND( NOT(ISBLANK($B1)), NOT(ISBLANK($C1)), NOT(ISBLANK($D1)) ), ISBLANK($A1)))"
A7: For Column B-D formatting | B7: "=AND(NOT( OR( NOT($A$2="Competitive"), AND( NOT(ISBLANK($B1)), NOT(ISBLANK($C1)), NOT(ISBLANK($D1)) ), ISBLANK($A1))), ISBLANK($C1))"
A8: For Vlookup | B8: "=IFERROR(IF(ISBLANK(D5),"",VLOOKUP(D5,'Competitor Options '!$A:$B,2,FALSE)),"")"

Sheet Competitor Options 
A2: 12GACUSTOMS | B2: GW0001
A3: 1800 RADIATOR | B3: GW0002
A4: 4 STATE TRUCKS | B4: GW0003
A5: A & M TRUCK PARTS | B5: GW0004
A6: A D BRAKES | B6: GW0005
A7: A1 TRUCK PARTS | B7: GW0006
A8: AA WHEEL & TRUCK SUPPLY | B8: GW0007
A9: ABC AUTO PART | B9: GW0008
A10: ABC BUS | B10: GW0009
A11: ACCESORIOS ALLENDE, S.A. DE C. | B11: GW0010
A12: ACPARTS.COM | B12: GW0011
A13: ACTION TRUCK PARTS | B13: GW0012
... A103: CAPITAL CLUTCH AND BRAKE | B103: GW0103
A104: CAPITAL GEAR | B104: GW0104 | C104: VILLAHERMOSA | D104: TB | E104: 86280
A105: CARCO INTERNATIONAL | B105: GW0105
A106: CARGO HEAVY DUTY | B106: GW0106
A107: CAROLINA INTERNATIONAL TRUCKS | B107: GW0107
A108: CAROLINA POWERTRAIN | B108: GW0108
A109: CARREFOUR DU CAMION | B109: GW0109
A110: CARRIER TRUCK CENTER | B110: GW0110
A111: CASTROL LUBRICANTS | B111: GW0111
A112: CBS Parts LTD | B112: GW0112
A113: CCC PARTS | B113: GW0113
A114: CENTRAL STATES BUS | B114: GW0114
A115: CENTRAL STATES THERMO KING | B115: GW0115
A116: CENTRAL TRANSPORT | B116: GW0116
... A606: Zoro Tools Inc | B606: GW0606
